ephemeral/__init__.py
ephemeral/data.py
ephemeral/static/main.css
ephemeral/static/node_modules/normalize.css/normalize.css
ephemeral/templates/add.html
ephemeral/templates/base.html
ephemeral/templates/link.html
ephemeral/templates/not_found.html
ephemeral/templates/pin.html
ephemeral/templates/root.html
ephemeral/templates/show.html
ephemeral/wsgi.py
ephemeral-0.1.5.data/scripts/ephemeral.sh
ephemeral-0.1.5.dist-info/LICENSE
ephemeral-0.1.5.dist-info/METADATA
ephemeral-0.1.5.dist-info/WHEEL
ephemeral-0.1.5.dist-info/entry_points.txt
ephemeral-0.1.5.dist-info/RECORD
