Metadata-Version: 2.1
Name: ephemeral
Version: 0.1.5
Summary: Self-destructing messages
Home-page: https://github.com/node13h/ephemeral
License: MIT
Author: Sergej Alikov
Author-email: sergej@alikov.com
Requires-Python: >=3.9,<4.0
Classifier: License :: OSI Approved :: MIT License
Classifier: Programming Language :: Python :: 3
Classifier: Programming Language :: Python :: 3.9
Classifier: Programming Language :: Python :: 3.10
Classifier: Programming Language :: Python :: 3.11
Requires-Dist: Flask (>=2.3,<3.0)
Requires-Dist: cryptography (>=41.0.3,<42.0.0)
Requires-Dist: gunicorn (>=21.2,<22.0)
Requires-Dist: redis (>=5.0,<6.0)
Project-URL: Repository, https://github.com/node13h/ephemeral
